.travis.yml
CHANGES.rst
MANIFEST.in
README.rst
setup.py
tox.ini
/home/blackwithwhite/Work/ged-soa/stats/src/pystat/src/cm_counter.c
/home/blackwithwhite/Work/ged-soa/stats/src/pystat/src/cm_heap.c
/home/blackwithwhite/Work/ged-soa/stats/src/pystat/src/cm_quantile.c
/home/blackwithwhite/Work/ged-soa/stats/src/pystat/src/cm_timer.c
pystat/__init__.py
pystat/counter.c
pystat/counter.pyx
pystat/plain_counter.c
pystat/plain_counter.pyx
pystat/timer.c
pystat/timer.pyx
pystat.egg-info/PKG-INFO
pystat.egg-info/SOURCES.txt
pystat.egg-info/dependency_links.txt
pystat.egg-info/not-zip-safe
pystat.egg-info/top_level.txt
pystat/tests/__init__.py
pystat/tests/base.py
pystat/tests/test_counter.py
pystat/tests/test_plain_counter.py
pystat/tests/test_timer.py
src/cm_counter.c
src/cm_counter.h
src/cm_heap.c
src/cm_heap.h
src/cm_quantile.c
src/cm_quantile.h
src/cm_timer.c
src/cm_timer.h